foreverbull/__init__.py
foreverbull/algorithm.py
foreverbull/exceptions.py
foreverbull/models.py
foreverbull/worker.py
foreverbull/broker/__init__.py
foreverbull/broker/backtest.py
foreverbull/broker/finance.py
foreverbull/broker/storage.py
foreverbull/pb/pb_utils.py
foreverbull/pb/buf/validate/validate_pb2.py
foreverbull/pb/buf/validate/validate_pb2.pyi
foreverbull/pb/buf/validate/validate_pb2_grpc.py
foreverbull/pb/foreverbull/common_pb2.py
foreverbull/pb/foreverbull/common_pb2.pyi
foreverbull/pb/foreverbull/common_pb2_grpc.py
foreverbull/pb/foreverbull/backtest/backtest_pb2.py
foreverbull/pb/foreverbull/backtest/backtest_pb2.pyi
foreverbull/pb/foreverbull/backtest/backtest_pb2_grpc.py
foreverbull/pb/foreverbull/backtest/backtest_service_pb2.py
foreverbull/pb/foreverbull/backtest/backtest_service_pb2.pyi
foreverbull/pb/foreverbull/backtest/backtest_service_pb2_grpc.py
foreverbull/pb/foreverbull/backtest/engine_service_pb2.py
foreverbull/pb/foreverbull/backtest/engine_service_pb2.pyi
foreverbull/pb/foreverbull/backtest/engine_service_pb2_grpc.py
foreverbull/pb/foreverbull/backtest/execution_pb2.py
foreverbull/pb/foreverbull/backtest/execution_pb2.pyi
foreverbull/pb/foreverbull/backtest/execution_pb2_grpc.py
foreverbull/pb/foreverbull/backtest/session_pb2.py
foreverbull/pb/foreverbull/backtest/session_pb2.pyi
foreverbull/pb/foreverbull/backtest/session_pb2_grpc.py
foreverbull/pb/foreverbull/backtest/session_service_pb2.py
foreverbull/pb/foreverbull/backtest/session_service_pb2.pyi
foreverbull/pb/foreverbull/backtest/session_service_pb2_grpc.py
foreverbull/pb/foreverbull/finance/finance_pb2.py
foreverbull/pb/foreverbull/finance/finance_pb2.pyi
foreverbull/pb/foreverbull/finance/finance_pb2_grpc.py
foreverbull/pb/foreverbull/finance/marketdata_service_pb2.py
foreverbull/pb/foreverbull/finance/marketdata_service_pb2.pyi
foreverbull/pb/foreverbull/finance/marketdata_service_pb2_grpc.py
foreverbull/pb/foreverbull/finance/trading_service_pb2.py
foreverbull-0.0.2503031831.dist-info/METADATA
foreverbull-0.0.2503031831.dist-info/WHEEL
foreverbull-0.0.2503031831.dist-info/top_level.txt
foreverbull-0.0.2503031831.dist-info/RECORD
