Metadata-Version: 2.2
Name: foreverbull
Version: 0.0.2503031831
Summary: foreverbull
Author-email: Henrik Nilsson <henrik@lhjnilsson.com>
Requires-Dist: pynng<1.0.0,>=0.8.0
Requires-Dist: minio<8.0.0,>=7.1.14
Requires-Dist: pandas<3.0.0,>=2.0.3
Requires-Dist: sqlalchemy<3.0.0,>=2.0.19
Requires-Dist: psycopg2-binary<3.0.0,>=2.9.1
Requires-Dist: click<9.0.0,>=8.0.1
Requires-Dist: cython<4.0,>=3.0.0
Requires-Dist: docker<8.0.0,>=7.0.0
Requires-Dist: pandas-datareader<1.0.0,>=0.10.0
Requires-Dist: tables<3.9.2
Requires-Dist: numpy<2.0.0
Requires-Dist: setuptools<71.0.0,>=70.2.0
Requires-Dist: protobuf==5.27.2
Requires-Dist: types-protobuf>=5.27.0.20240626
Requires-Dist: grpcio>=1.66.1
